[

    {

        "img1": "https://yanxuan-item.nosdn.127.net/11fe945e048cfc5d94be5951d796f118.png?type=webp&quality=95&thumbnail=265x265&imageView",
        "imgHover": "https://yanxuan-item.nosdn.127.net/4e78ea9bf47fc7c70d55f20838b834fb.jpg?type=webp&quality=95&thumbnail=265x265&imageView",
        "smallTitle": "新品尝鲜",
        "span1": "¥49",
        "promContent": "限500件 仅剩1天",
        "h4": "富士山の便携加湿器",
        "price": "49",
        "yuanjia": "59"
    },
    {

        "img1": "https://yanxuan-item.nosdn.127.net/f8b80d9cfb95573de5ffe3ad8ac3e9fe.png?type=webp&quality=95&thumbnail=265x265&imageView",
        "imgHover": "https://yanxuan-item.nosdn.127.net/ba9db3e72f3be6999e864a97f816f301.png?type=webp&quality=95&thumbnail=265x265&imageView",
        "smallTitle": "11.11",
        "span1": "定金预售",
        "promContent": "40抵129 仅剩10天",
        "h4": "男式潮流拼接户外老爹鞋",
        "price": "280",
        "yuanjia": "369"
    },
    {
        "img1": "https://yanxuan-item.nosdn.127.net/0d7f0028d1cb07ef67f2a865cbe9dbe6.png?type=webp&quality=95&thumbnail=265x265&imageView",
        "imgHover": "https://yanxuan-item.nosdn.127.net/efaa07b6833d7d257eac7383dbfed0cc.png?type=webp&quality=95&thumbnail=265x265&imageView",
        "span1": "专场限时购",
        "span2": "¥209",
        "promContent": "11月1日 0点开抢",
        "h4": "女式羊毛内里乐福鞋2.0",
        "price": "299",
        "yuanjia": "299"
    },
    {
        "img1": "https://yanxuan-item.nosdn.127.net/e30c0db59fc806365bb92ffb4851e350.png?type=webp&quality=95&thumbnail=265x265&imageView",
        "imgHover": "https://yanxuan-item.nosdn.127.net/3da30c0fba03cae111ca0a9996a17946.png?type=webp&quality=95&thumbnail=265x265&imageView",
        "span1": "11.11",
        "span2": "定金预售",
        "promContent": "139抵489 仅剩10天",
        "h4": "男式地表强温宽松羽绒服",
        "price": "949",
        "yuanjia": "1299"
    },
    {
        "img1": "https://yanxuan-item.nosdn.127.net/e277aa8352b720eab2f6afae5dcabcc1.png?type=webp&quality=95&thumbnail=265x265&imageView",
        "imgHover": "https://yanxuan-item.nosdn.127.net/e4bfd5aa1abf34e4fa7d6d583a2d1d71.jpg?type=webp&quality=95&thumbnail=265x265&imageView",
        "span1": "11.11",
        "span2": "定金预售",
        "promContent": "149抵249 仅剩10天",
        "h4": "踢脚线取暖器",
        "price": "799",
        "yuanjia": "899"
    },
    {
        "img1": "https://yanxuan-item.nosdn.127.net/ff2b35fc5025fc737e8a5f79206604bf.png?type=webp&quality=95&thumbnail=265x265&imageView",
        "imgHover": "https://yanxuan-item.nosdn.127.net/0c3b29d6b511661ed239949e509b5f08.jpg?type=webp&quality=95&thumbnail=265x265&imageView",
        "span1": "新品粉丝价",
        "span2": "¥23.9",
        "promContent": "11月2日 0点开抢",
        "h4": "浓缩型衣物除螨除菌液 1L/3L",
        "price": "29.9",
        "yuanjia": "29.9"
    },
    {
        "img1": "https://yanxuan-item.nosdn.127.net/f3017836b70b5e7f8c9a487bf45d496f.png?type=webp&quality=95&thumbnail=265x265&imageView",
        "imgHover": "https://yanxuan-item.nosdn.127.net/bf04484f8ea980c81f8d77285c85352e.png?type=webp&quality=95&thumbnail=265x265&imageView",
        "span1": "专场限时购",
        "span2": "¥179",
        "promContent": "11月1日 0点开抢",
        "h4": "网易智造日式保鲜蒸煮饭盒",
        "price": "229",
        "yuanjia": "229"
    },
    {
        "img1": "https://yanxuan-item.nosdn.127.net/a48cd91b348aac3661a1e43f23aa83a6.png?type=webp&quality=95&thumbnail=265x265&imageView",
        "imgHover": "https://yanxuan-item.nosdn.127.net/75a28e176803c3f2b0b3bd5c75ab19df.jpg?type=webp&quality=95&thumbnail=265x265&imageView",
        "span1": "8折券提前抢",
        "span2": "10.29-10.31",
        "promContent": "开通超会享优惠",
        "h4": "烟熏鱿鱼 100克",
        "price": "19",
        "yuanjia": "19"
    },
    {
        "img1": "https://yanxuan-item.nosdn.127.net/b21be99956b315be359df338e9140555.png?type=webp&quality=95&thumbnail=265x265&imageView",
        "imgHover": "https://yanxuan-item.nosdn.127.net/75a28e176803c3f2b0b3bd5c75ab19df.jpg?type=webp&quality=95&thumbnail=265x265&imageView",
        "span1": "8折券提前抢",
        "span2": "10.29-10.31",
        "promContent": "开通超会享优惠",
        "h4": "烟熏鱿鱼 100克",
        "price": "19",
        "yuanjia": "19"
    },
    {
        "img1": "https://yanxuan-item.nosdn.127.net/44dfa5a0a9f9b36d9d370034a9c6f82b.png?type=webp&quality=95&thumbnail=265x265&imageView",
        "imgHover": "https://yanxuan-item.nosdn.127.net/82524aa902b8865a81d9e673fc6e15ae.jpeg?type=webp&quality=95&thumbnail=265x265&imageView",
        "span1": "新品粉丝价",
        "span2": "¥49.9",
        "promContent": "11月2日 0点开抢",
        "h4": "家居玩具宠物杀菌除螨通用消毒液 1.5L",
        "price": "59.9",
        "yuanjia": "59.9"
    },
    {
        "img1": "https://yanxuan-item.nosdn.127.net/2d66db7d92246aa5a6b3da2f053bc6a2.png?type=webp&quality=95&thumbnail=265x265&imageView",
        "imgHover": "https://yanxuan-item.nosdn.127.net/86bb5c5f4a87f52a18c983184fedd6fc.jpg?type=webp&quality=95&thumbnail=265x265&imageView",
        "span1": "新品粉丝价",
        "span2": "¥29.9",
        "promContent": "11月2日 0点开抢",
        "h4": "持久顺滑眼线液笔  2色可选",
        "price": "39.9",
        "yuanjia": "39.9"
    },
    {
        "img1": "https://yanxuan-item.nosdn.127.net/17d6eece13217472874957704dab77de.png?type=webp&quality=95&thumbnail=265x265&imageView",
        "imgHover": "https://yanxuan-item.nosdn.127.net/dfd10fab545d1f82e05ad14369f5b1d8.jpg?type=webp&quality=95&thumbnail=265x265&imageView",
        "span1": "新品粉丝价",
        "span2": "¥11.9",
        "promContent": "11月2日 0点开抢",
        "h4": "强效毛发分解抑菌管道疏通剂 500g",
        "price": "14.9",
        "yuanjia": "14.9"
    },
    {
        "img1": "https://yanxuan-item.nosdn.127.net/47e60d7482293934a9e033e8de20b53e.png?type=webp&quality=95&thumbnail=265x265&imageView",
        "imgHover": "https://yanxuan-item.nosdn.127.net/927306e58d83cc695069f951c3866987.png?type=webp&quality=95&thumbnail=265x265&imageView",
        "span1": "限时购",
        "span2": "¥39",
        "promContent": "11月1日 10点开抢",
        "h4": "新西兰制造 3.6g乳蛋白全脂纯牛奶",
        "price": "49.9",
        "yuanjia": "49.9"
    },
    {
        "img1": "https://yanxuan-item.nosdn.127.net/e11da4874bb640fb5ebac7ae3b359a16.png?type=webp&quality=95&thumbnail=265x265&imageView",
        "imgHover": "https://yanxuan-item.nosdn.127.net/bfcfc47c65d50971ed0674c4ff12d2c8.jpg?type=webp&quality=95&thumbnail=265x265&imageView",
        "span1": "11.11",
        "span2": "定金预售",
        "promContent": "39抵118 仅剩10天",
        "h4": "2个装 泰国制造 低枕怡眠天然乳胶枕",
        "price": "279",
        "yuanjia": "358"
    },
    {
        "img1": "https://yanxuan-item.nosdn.127.net/22e04dd7d8390ac4338b203ccf34da23.png?type=webp&quality=95&thumbnail=265x265&imageView",
        "imgHover": "https://yanxuan-item.nosdn.127.net/6e19979235b95d51c09f254cb2b01323.jpg?type=webp&quality=95&thumbnail=265x265&imageView",
        "span1": "8折券提前抢",
        "span2": "10.29-10.31",
        "promContent": "开通超会享优惠",
        "h4": "12星座吉他拨片吊坠",
        "price": "28",
        "yuanjia": "28"
    },
    {
        "img1": "https://yanxuan-item.nosdn.127.net/84d1c8ddf611ec9a0f5e489debfd71dc.png?type=webp&quality=95&thumbnail=265x265&imageView",
        "imgHover": "https://yanxuan-item.nosdn.127.net/aa8ca38261c07d1d9f5f47a0004a8ef2.jpg?type=webp&quality=95&thumbnail=265x265&imageView",
        "span1": "8折券提前抢",
        "span2": "10.29-10.31",
        "promContent": "开通超会享优惠",
        "h4": "贵州乌杆天麻礼盒  250克",
        "price": "298",
        "yuanjia": "298"
    },
    {
        "img1": "https://yanxuan-item.nosdn.127.net/d5da8012df05568659ad743c492fc428.png?type=webp&quality=95&thumbnail=265x265&imageView",
        "imgHover": "https://yanxuan-item.nosdn.127.net/30ff1cc687fe550b7ae5a5c040063a6b.jpg?type=webp&quality=95&thumbnail=265x265&imageView",
        "span1": "狂欢特惠",
        "span2": "¥179",
        "promContent": "仅剩1天",
        "h4": "新会老陈皮",
        "price": "179",
        "yuanjia": "199"
    },
    {
        "img1": "https://yanxuan-item.nosdn.127.net/81c5d49bbc4448ea81639946a6dec491.png?type=webp&quality=95&thumbnail=265x265&imageView",
        "imgHover": "https://yanxuan-item.nosdn.127.net/673056f5f759a81029a8fe3412ad96a4.jpg?type=webp&quality=95&thumbnail=265x265&imageView",
        "span1": "新品粉丝价",
        "span2": "¥11.9",
        "promContent": "11月2日 0点开抢",
        "h4": "防霉除垢抑菌玻璃清洁剂500g 家用车用",
        "price": "14.9",
        "yuanjia": "14.9"
    },
    {
        "img1": "https://yanxuan-item.nosdn.127.net/f40ff867e229b9b680b26193549592de.png?type=webp&quality=95&thumbnail=265x265&imageView",
        "imgHover": "https://yanxuan-item.nosdn.127.net/483d63c1249af002e408e38bdd51896c.png?type=webp&quality=95&thumbnail=265x265&imageView",
        "span1": "新款羽绒服",
        "span2": "¥799",
        "promContent": "11月5日 0点开抢",
        "h4": "男式时尚短款羽绒服",
        "price": "799",
        "yuanjia": "799"
    },
    {
        "img1": "https://yanxuan-item.nosdn.127.net/ea438e03f93380aa3998818d195d702c.png?type=webp&quality=95&thumbnail=265x265&imageView",
        "imgHover": "https://yanxuan-item.nosdn.127.net/248110d73f574a269a20f0b3e3da4e5b.png?type=webp&quality=95&thumbnail=265x265&imageView",
        "span1": "新款羽绒服",
        "span2": "¥999",
        "promContent": "11月3日 8点开抢",
        "h4": "男式防风长款羽绒服",
        "price": "999",
        "yuanjia": "999"
    },
    {
        "img1": "https://yanxuan-item.nosdn.127.net/3cbd733aeda04e847094322097c7c35c.png?type=webp&quality=95&thumbnail=265x265&imageView",
        "imgHover": "https://yanxuan-item.nosdn.127.net/4e78ea9bf47fc7c70d55f20838b834fb.jpg?type=webp&quality=95&thumbnail=265x265&imageView",
        "span1": "新品尝鲜",
        "span2": "¥49",
        "promContent": "限500件 仅剩1天",
        "h4": "富士山の便携加湿器",
        "price": "49",
        "yuanjia": "59"
    },
    {
        "img1": "https://yanxuan-item.nosdn.127.net/7fa958a5178a6f66d1b31520c471473d.png?type=webp&quality=95&thumbnail=265x265&imageView",
        "imgHover": "https://yanxuan-item.nosdn.127.net/1e1b8684cb50161f35da1615b9f41872.jpg?type=webp&quality=95&thumbnail=265x265&imageView",
        "span1": "8折券提前抢",
        "span2": "10.29-10.31",
        "promContent": "开通超会享优惠",
        "h4": "五谷杂粮粥粉 300克",
        "price": "39",
        "yuanjia": "39"
    },
    {
        "img1": "https://yanxuan-item.nosdn.127.net/b63b5033e8b2cfc1f41671494bc2ff2b.png?type=webp&quality=95&thumbnail=265x265&imageView",
        "imgHover": "https://yanxuan-item.nosdn.127.net/1187365e2b8ea319b430024b59c6c2ca.jpg?type=webp&quality=95&thumbnail=265x265&imageView",
        "span1": "新品尝鲜价",
        "span2": "¥34.9",
        "promContent": "限500件 仅剩10天",
        "h4": "USB-C PD快充电源适配器（18W）",
        "price": "34.9",
        "yuanjia": "39"
    },
    {
        "img1": "https://yanxuan-item.nosdn.127.net/18fdb92a946b74a80df67e9e95b15ef8.png?type=webp&quality=95&thumbnail=265x265&imageView",
        "imgHover": "https://yanxuan-item.nosdn.127.net/abfdd6eb2ad2242585e56a1647f6b988.jpg?type=webp&quality=95&thumbnail=265x265&imageView",
        "span1": "狂欢特惠",
        "span2": "¥849",
        "promContent": "仅剩10天",
        "h4": "多维降噪破壁机",
        "price": "849",
        "yuanjia": "999"
    },
    {
        "img1": "https://yanxuan-item.nosdn.127.net/2f259c4e173301519b9765565af87a68.png?type=webp&quality=95&thumbnail=265x265&imageView",
        "imgHover": "https://yanxuan-item.nosdn.127.net/81c2ab278e8c16e1b4a9fd8b42acc56c.jpg?type=webp&quality=95&thumbnail=265x265&imageView",
        "span1": "8折券提前抢",
        "span2": "10.29-10.31",
        "promContent": "开通超会享优惠",
        "h4": "是谁嗯嗯在我的头上",
        "price": "32",
        "yuanjia": "32"
    },
    {
        "img1": "https://yanxuan-item.nosdn.127.net/d373d3aa6d9e7143ecaea19e605b7a08.png?type=webp&quality=95&thumbnail=265x265&imageView",
        "imgHover": "https://yanxuan-item.nosdn.127.net/9584fe2dd822a82a608b56913139a2f2.jpg?type=webp&quality=95&thumbnail=265x265&imageView",
        "span1": "8折券提前抢",
        "span2": "10.29-10.31",
        "promContent": "开通超会享优惠",
        "h4": "花婆婆",
        "price": "26.5",
        "yuanjia": "26.5"
    },
    {
        "img1": "https://yanxuan-item.nosdn.127.net/0b457db9d05da139e89217735bbf80a1.png?type=webp&quality=95&thumbnail=265x265&imageView",
        "imgHover": "https://yanxuan-item.nosdn.127.net/7945774d904c97f2141bf79532ee6db2.jpg?type=webp&quality=95&thumbnail=265x265&imageView",
        "span1": "11.11",
        "span2": "定金预售",
        "promContent": "29抵90 仅剩10天",
        "h4": "妈咪两用纯棉柔巾 100抽*10包",
        "price": "129",
        "yuanjia": "190"
    },
    {
        "img1": "https://yanxuan-item.nosdn.127.net/8d553ec5b79b53dbb015df481b982593.png?type=webp&quality=95&thumbnail=265x265&imageView",
        "imgHover": "https://yanxuan-item.nosdn.127.net/6c6c1903bd5c4c0beb7cb9eccf3b7934.jpg?type=webp&quality=95&thumbnail=265x265&imageView",
        "span1": "11.11",
        "span2": "定金预售",
        "promContent": "29抵88 仅剩10天",
        "h4": "宝宝肌超柔乳霜纸巾100抽*36包",
        "price": "169",
        "yuanjia": "228"
    },
    {
        "img1": "https://yanxuan-item.nosdn.127.net/8d553ec5b79b53dbb015df481b982593.png?type=webp&quality=95&thumbnail=265x265&imageView",
        "imgHover": "https://yanxuan-item.nosdn.127.net/6c6c1903bd5c4c0beb7cb9eccf3b7934.jpg?type=webp&quality=95&thumbnail=265x265&imageView",
        "span1": "11.11",
        "span2": "定金预售",
        "promContent": "29抵88 仅剩10天",
        "h4": "宝宝肌超柔乳霜纸巾100抽*36包",
        "price": "169",
        "yuanjia": "228"
    },
    {
        "img1": "https://yanxuan-item.nosdn.127.net/ea375b226d15109d12bcbe4db744fad1.png?type=webp&quality=95&thumbnail=265x265&imageView",
        "imgHover": "https://yanxuan-item.nosdn.127.net/3d2e7070385678e99bbcc869a2d3ca48.jpg?type=webp&quality=95&thumbnail=265x265&imageView",
        "span1": "狂欢特惠",
        "span2": "¥69",
        "promContent": "仅剩15天",
        "h4": "金秋红蜜桃 4.5斤",
        "price": "69",
        "yuanjia": "79"
    },
    {
        "img1": "https://yanxuan-item.nosdn.127.net/440f7a5e977cfd130aa84a69db4be174.png?type=webp&quality=95&thumbnail=265x265&imageView",
        "imgHover": "https://yanxuan-item.nosdn.127.net/6f78ded698fab744220d4c53f657240c.jpg?type=webp&quality=95&thumbnail=265x265&imageView",
        "span1": "狂欢特惠",
        "span2": "¥53",
        "promContent": "仅剩15天",
        "h4": "大凉山盐源丑苹果 5斤",
        "price": "53",
        "yuanjia": "58"
    }

]